{
  "updated_at": "2026-07-16T08:21:15.318748+08:00",
  "weather": "石崗現況 25°C 元朗公園 · 濕度 94% · 石崗2小時內有機會落雨 · 大致多雲，間中有驟雨及幾陣狂風雷暴。初時雨勢有時頗大。最高氣溫約29度。吹和緩至清勁南至西南風。",
  "bus": [
    {
      "route": "251A",
      "dest": "上村",
      "type": "KMB",
      "clocks": [
        "08:24",
        "08:44",
        "09:04"
      ],
      "rels": [
        "3分鐘內",
        "23分鐘",
        "43分鐘"
      ]
    },
    {
      "route": "64K",
      "dest": "大埔墟站",
      "type": "KMB",
      "clocks": [
        "08:29",
        "08:41",
        "08:56"
      ],
      "rels": [
        "8分鐘",
        "20分鐘",
        "35分鐘"
      ]
    },
    {
      "route": "64K",
      "dest": "元朗(西)",
      "type": "KMB",
      "clocks": [
        "08:30",
        "08:49",
        "08:57"
      ],
      "rels": [
        "9分鐘",
        "29分鐘",
        "36分鐘"
      ]
    },
    {
      "route": "71",
      "dest": "河背",
      "type": "GMB",
      "clocks": [
        "08:25",
        "08:35",
        "08:49"
      ],
      "rels": [
        "5分鐘",
        "15分鐘",
        "28分鐘"
      ]
    },
    {
      "route": "71",
      "dest": "元朗",
      "type": "GMB",
      "clocks": [
        "08:43",
        "08:58",
        "09:13"
      ],
      "rels": [
        "22分鐘",
        "37分鐘",
        "52分鐘"
      ]
    },
    {
      "route": "71A",
      "dest": "長莆",
      "type": "GMB",
      "clocks": [
        "08:21",
        "08:34",
        "08:54"
      ],
      "rels": [
        "即將到",
        "13分鐘",
        "33分鐘"
      ]
    },
    {
      "route": "71A",
      "dest": "錦上路站",
      "type": "GMB",
      "clocks": [
        "08:57",
        "09:17"
      ],
      "rels": [
        "36分鐘",
        "56分鐘"
      ]
    }
  ]
}