{
  "updated_at": "2026-07-18T14:54:32.530156+08:00",
  "weather": "石崗現況 29°C 元朗公園 · 濕度 82% · 石崗2小時內有機會落雨 · 大致多雲，有幾陣驟雨及雷暴。吹和緩南至西南風。",
  "bus": [
    {
      "route": "251A",
      "dest": "上村",
      "type": "KMB",
      "clocks": [
        "15:09",
        "15:29",
        "15:49"
      ],
      "rels": [
        "15分鐘",
        "35分鐘",
        "55分鐘"
      ]
    },
    {
      "route": "64K",
      "dest": "大埔墟站",
      "type": "KMB",
      "clocks": [
        "14:55",
        "14:58",
        "15:05"
      ],
      "rels": [
        "1分鐘內",
        "4分鐘",
        "11分鐘"
      ]
    },
    {
      "route": "64K",
      "dest": "元朗(西)",
      "type": "KMB",
      "clocks": [
        "14:55",
        "15:02",
        "15:24"
      ],
      "rels": [
        "1分鐘內",
        "8分鐘",
        "30分鐘"
      ]
    },
    {
      "route": "71",
      "dest": "河背",
      "type": "GMB",
      "clocks": [
        "14:55",
        "14:59",
        "15:10"
      ],
      "rels": [
        "1分鐘內",
        "5分鐘",
        "16分鐘"
      ]
    },
    {
      "route": "71",
      "dest": "元朗",
      "type": "GMB",
      "clocks": [
        "15:10",
        "15:25",
        "15:40"
      ],
      "rels": [
        "16分鐘",
        "31分鐘",
        "46分鐘"
      ]
    },
    {
      "route": "71A",
      "dest": "長莆",
      "type": "GMB",
      "clocks": [
        "15:13",
        "15:33"
      ],
      "rels": [
        "19分鐘",
        "39分鐘"
      ]
    },
    {
      "route": "71A",
      "dest": "錦上路站",
      "type": "GMB",
      "clocks": [
        "15:06",
        "15:36"
      ],
      "rels": [
        "12分鐘",
        "42分鐘"
      ]
    }
  ]
}