{
  "updated_at": "2026-07-22T14:08:05.715352+08:00",
  "weather": "石崗現況 34°C 元朗公園 · 濕度 61% · 石崗2小時內有機會落雨 · 大致天晴。下午酷熱，但局部地區有驟雨。吹和緩偏南風。",
  "bus": [
    {
      "route": "251A",
      "dest": "上村",
      "type": "KMB",
      "clocks": [
        "14:24",
        "14:44",
        "15:03"
      ],
      "rels": [
        "16分鐘",
        "36分鐘",
        "56分鐘"
      ]
    },
    {
      "route": "64K",
      "dest": "大埔墟站",
      "type": "KMB",
      "clocks": [
        "14:12",
        "14:12",
        "14:23"
      ],
      "rels": [
        "4分鐘",
        "4分鐘",
        "16分鐘"
      ]
    },
    {
      "route": "64K",
      "dest": "元朗(西)",
      "type": "KMB",
      "clocks": [
        "14:19",
        "14:27",
        "14:36"
      ],
      "rels": [
        "11分鐘",
        "20分鐘",
        "29分鐘"
      ]
    },
    {
      "route": "71",
      "dest": "河背",
      "type": "GMB",
      "clocks": [
        "14:18",
        "14:34",
        "14:49"
      ],
      "rels": [
        "10分鐘",
        "27分鐘",
        "42分鐘"
      ]
    },
    {
      "route": "71",
      "dest": "元朗",
      "type": "GMB",
      "clocks": [
        "14:26",
        "14:41",
        "14:56"
      ],
      "rels": [
        "19分鐘",
        "34分鐘",
        "49分鐘"
      ]
    },
    {
      "route": "71A",
      "dest": "長莆",
      "type": "GMB",
      "clocks": [
        "14:11",
        "14:24",
        "14:44"
      ],
      "rels": [
        "3分鐘內",
        "16分鐘",
        "36分鐘"
      ]
    },
    {
      "route": "71A",
      "dest": "錦上路站",
      "type": "GMB",
      "clocks": [
        "14:18",
        "14:45",
        "15:05"
      ],
      "rels": [
        "11分鐘",
        "38分鐘",
        "58分鐘"
      ]
    }
  ]
}